DataAnalysisEnedis/Database.py
DataAnalysisEnedis/Decryptage.py
DataAnalysisEnedis/Flux.py
DataAnalysisEnedis/__init__.py
DataAnalysisEnedis/core.py
tests/DataAnalysis_enedis_test.py
tests/__init__.py
DataAnalysisEnedis-0.1.0.dist-info/LICENSE
DataAnalysisEnedis-0.1.0.dist-info/METADATA
DataAnalysisEnedis-0.1.0.dist-info/WHEEL
DataAnalysisEnedis-0.1.0.dist-info/top_level.txt
DataAnalysisEnedis-0.1.0.dist-info/RECORD
