Metadata-Version: 2.1
Name: DataAnalysisEnedis
Version: 0.1.0
Summary: DataAnalysis_enedis est une classe Python conçue pour faciliter l'analyse de données dans le cadre de la gestion de flux de données d'Enedis
Home-page: https://github.com/ZephyrIt0/DataAnalysisEnedis
Author: gld
Author-email: dimbugrace@gmail.com
Classifier: Programming Language :: Python :: 3
Classifier: License :: OSI Approved :: MIT License
Classifier: Operating System :: OS Independent
Requires-Python: >=3.6
License-File: LICENSE
Requires-Dist: pyodbc
Requires-Dist: pandas
Requires-Dist: sqlalchemy
Requires-Dist: pycryptodome
Requires-Dist: alive-progress
Requires-Dist: pysftp
